yori/IOtools.py
yori/__init__.py
yori/aggrtools.py
yori/config_reader.py
yori/gridtools.py
yori/run_yori.py
yori/yori_aggregate.py
yori/yori_merge.py
yori/tools/__init__.py
yori/tools/aggr.py
yori/tools/grid.py
yori/tools/merge.py
yori-1.7.21.dist-info/METADATA
yori-1.7.21.dist-info/WHEEL
yori-1.7.21.dist-info/entry_points.txt
yori-1.7.21.dist-info/licenses/LICENSE
yori-1.7.21.dist-info/RECORD
