Metadata-Version: 2.4
Name: yori
Version: 1.7.21
Summary: User-customizable set of tools to easily grid satellite data
Project-URL: Homepage, https://gitlab.ssec.wisc.edu/pveglio/yori
Project-URL: Documentation, https://sips.ssec.wisc.edu/docs/yori.html
Project-URL: Changelog, https://gitlab.ssec.wisc.edu/pveglio/yori/-/blob/master/CHANGELOG.md
Author-email: Paolo Veglio <paolo.veglio@ssec.wisc.edu>
License-File: LICENSE
Classifier: Development Status :: 5 - Production/Stable
Classifier: License :: OSI Approved :: MIT License
Classifier: Programming Language :: Python :: 3.9
Classifier: Programming Language :: Python :: 3.10
Classifier: Programming Language :: Python :: 3.11
Classifier: Programming Language :: Python :: 3.12
Classifier: Programming Language :: Python :: Implementation :: CPython
Requires-Python: >=3.10
Requires-Dist: netcdf4
Requires-Dist: numpy==1.25.1
Requires-Dist: pyproj
Requires-Dist: ruamel-yaml
Requires-Dist: setuptools
